verilog/dff.v
module dff(
    input wire clk,
    input wire rst,  
    input wire d,
    output reg q
);
    
    always @(posedge clk) begin
        if (rst)
            q <= 1'b0;
        else
            q <= d;
    end
    
endmodule

verilog/cla_adder_5bit.v
module cla_adder_5bit (
    input wire clk,
    input wire [4:0] a,
    input wire [4:0] b,
    output wire [4:0] sum,
    output wire cout
);

    wire [4:0] a_reg, b_reg;
    wire [4:0] p, g;
    wire [5:0] c;
    wire [4:0] sum_wire;

    // Register inputs
    dff a_reg0 (.clk(clk), .d(a[0]), .q(a_reg[0]));
    dff a_reg1 (.clk(clk), .d(a[1]), .q(a_reg[1]));
    dff a_reg2 (.clk(clk), .d(a[2]), .q(a_reg[2]));
    dff a_reg3 (.clk(clk), .d(a[3]), .q(a_reg[3]));
    dff a_reg4 (.clk(clk), .d(a[4]), .q(a_reg[4]));

    dff b_reg0 (.clk(clk), .d(b[0]), .q(b_reg[0]));
    dff b_reg1 (.clk(clk), .d(b[1]), .q(b_reg[1]));
    dff b_reg2 (.clk(clk), .d(b[2]), .q(b_reg[2]));
    dff b_reg3 (.clk(clk), .d(b[3]), .q(b_reg[3]));
    dff b_reg4 (.clk(clk), .d(b[4]), .q(b_reg[4]));

    // Propagate
    xor p0_xor(p[0], a_reg[0], b_reg[0]);
    xor p1_xor(p[1], a_reg[1], b_reg[1]);
    xor p2_xor(p[2], a_reg[2], b_reg[2]);
    xor p3_xor(p[3], a_reg[3], b_reg[3]);
    xor p4_xor(p[4], a_reg[4], b_reg[4]);

    // Generate
    and g0_and(g[0], a_reg[0], b_reg[0]);
    and g1_and(g[1], a_reg[1], b_reg[1]);
    and g2_and(g[2], a_reg[2], b_reg[2]);
    and g3_and(g[3], a_reg[3], b_reg[3]);
    and g4_and(g[4], a_reg[4], b_reg[4]);

    // Carry-in
    assign c[0] = 1'b0;

    // C1 = g0 + p0*c0
    wire c1_and;
    and c1_and_gate(c1_and, p[0], c[0]);
    or  c1_or_gate(c[1], g[0], c1_and);

    // C2 = g1 + p1*g0 + p1*p0*c0
    wire c2_and1, c2_and2, c2_or1;
    and c2_and_gate1(c2_and1, p[1], g[0]);
    and c2_and_gate2(c2_and2, p[1], p[0], c[0]);
    or  c2_or_gate1(c2_or1, g[1], c2_and1);
    or  c2_or_gate2(c[2], c2_or1, c2_and2);

    // C3 = g2 + p2*g1 + p2*p1*g0 + p2*p1*p0*c0
    wire c3_and1, c3_and2, c3_and3, c3_or1, c3_or2;
    and c3_and_gate1(c3_and1, p[2], g[1]);
    and c3_and_gate2(c3_and2, p[2], p[1], g[0]);
    and c3_and_gate3(c3_and3, p[2], p[1], p[0], c[0]);
    or  c3_or_gate1(c3_or1, g[2], c3_and1);
    or  c3_or_gate2(c3_or2, c3_or1, c3_and2);
    or  c3_or_gate3(c[3], c3_or2, c3_and3);

    // C4 = g3 + p3*g2 + p3*p2*g1 + p3*p2*p1*g0 + p3*p2*p1*p0*c0
    wire c4_and1, c4_and2, c4_and3, c4_and4, c4_or1, c4_or2, c4_or3;
    and c4_and_gate1(c4_and1, p[3], g[2]);
    and c4_and_gate2(c4_and2, p[3], p[2], g[1]);
    and c4_and_gate3(c4_and3, p[3], p[2], p[1], g[0]);
    and c4_and_gate4(c4_and4, p[3], p[2], p[1], p[0], c[0]);
    or  c4_or_gate1(c4_or1, g[3], c4_and1);
    or  c4_or_gate2(c4_or2, c4_or1, c4_and2);
    or  c4_or_gate3(c4_or3, c4_or2, c4_and3);
    or  c4_or_gate4(c[4], c4_or3, c4_and4);

    // C5 = g4 + p4*g3 + p4*p3*g2 + p4*p3*p2*g1 + p4*p3*p2*p1*g0 + p4*p3*p2*p1*p0*c0
    wire c5_and1, c5_and2, c5_and3, c5_and4, c5_and5, c5_or1, c5_or2, c5_or3, c5_or4;
    and c5_and_gate1(c5_and1, p[4], g[3]);
    and c5_and_gate2(c5_and2, p[4], p[3], g[2]);
    and c5_and_gate3(c5_and3, p[4], p[3], p[2], g[1]);
    and c5_and_gate4(c5_and4, p[4], p[3], p[2], p[1], g[0]);
    and c5_and_gate5(c5_and5, p[4], p[3], p[2], p[1], p[0], c[0]);
    or  c5_or_gate1(c5_or1, g[4], c5_and1);
    or  c5_or_gate2(c5_or2, c5_or1, c5_and2);
    or  c5_or_gate3(c5_or3, c5_or2, c5_and3);
    or  c5_or_gate4(c5_or4, c5_or3, c5_and4);
    or  c5_or_gate5(c[5], c5_or4, c5_and5);

    // Sum bits
    xor sum0_xor(sum_wire[0], p[0], c[0]);
    xor sum1_xor(sum_wire[1], p[1], c[1]);
    xor sum2_xor(sum_wire[2], p[2], c[2]);
    xor sum3_xor(sum_wire[3], p[3], c[3]);
    xor sum4_xor(sum_wire[4], p[4], c[4]);

    // Register outputs
    dff sum_reg0 (.clk(clk), .d(sum_wire[0]), .q(sum[0]));
    dff sum_reg1 (.clk(clk), .d(sum_wire[1]), .q(sum[1]));
    dff sum_reg2 (.clk(clk), .d(sum_wire[2]), .q(sum[2]));
    dff sum_reg3 (.clk(clk), .d(sum_wire[3]), .q(sum[3]));
    dff sum_reg4 (.clk(clk), .d(sum_wire[4]), .q(sum[4]));
    dff cout_reg  (.clk(clk), .d(c[5]),     .q(cout));

endmodule

verilog/cla_adder_5bit_tb.v
module cla_adder_5bit_tb;
    reg clk;
    reg [4:0] a, b;
    wire [4:0] sum;
    wire cout;

    cla_adder_5bit uut (
        .clk(clk),
        .a(a),
        .b(b),
        .sum(sum),
        .cout(cout)
    );

    initial begin
        clk = 0;
        forever #50 clk = ~clk;
    end

    initial begin
        $dumpfile("cla_adder_5bit.vcd");
        $dumpvars(0, cla_adder_5bit_tb);

        a = 5'b00000; b = 5'b00000;
        #100;

        a = 5'b00001; b = 5'b00001;
        #100;

        a = 5'b11111; b = 5'b00001;
        #100;

        a = 5'b10101; b = 5'b01010;
        #100;

        a = 5'b00000; b = 5'b11111;
        #100;

        a = 5'b11111; b = 5'b11111;
        #100;

        a = 5'b11111; b = 5'b11101;   
        #100;

        #100;
        $finish;
    end
endmodule

verilog/cla_adder_5bit.vcd
$date
	Tue Dec 02 10:50:20 2025
$end
$version
	Icarus Verilog
$end
$timescale
	1s
$end
$scope module cla_adder_5bit_tb $end
$var wire 5 ! sum [4:0] $end
$var wire 1 " cout $end
$var reg 5 # a [4:0] $end
$var reg 5 $ b [4:0] $end
$var reg 1 % clk $end
$scope module uut $end
$var wire 5 & a [4:0] $end
$var wire 5 ' b [4:0] $end
$var wire 1 ( c1_and $end
$var wire 1 ) c2_and1 $end
$var wire 1 * c2_and2 $end
$var wire 1 + c2_or1 $end
$var wire 1 , c3_and1 $end
$var wire 1 - c3_and2 $end
$var wire 1 . c3_and3 $end
$var wire 1 / c3_or1 $end
$var wire 1 0 c3_or2 $end
$var wire 1 1 c4_and1 $end
$var wire 1 2 c4_and2 $end
$var wire 1 3 c4_and3 $end
$var wire 1 4 c4_and4 $end
$var wire 1 5 c4_or1 $end
$var wire 1 6 c4_or2 $end
$var wire 1 7 c4_or3 $end
$var wire 1 8 c5_and1 $end
$var wire 1 9 c5_and2 $end
$var wire 1 : c5_and3 $end
$var wire 1 ; c5_and4 $end
$var wire 1 < c5_and5 $end
$var wire 1 = c5_or1 $end
$var wire 1 > c5_or2 $end
$var wire 1 ? c5_or3 $end
$var wire 1 @ c5_or4 $end
$var wire 1 % clk $end
$var wire 5 A sum_wire [4:0] $end
$var wire 5 B sum [4:0] $end
$var wire 5 C p [4:0] $end
$var wire 5 D g [4:0] $end
$var wire 1 " cout $end
$var wire 6 E c [5:0] $end
$var wire 5 F b_reg [4:0] $end
$var wire 5 G a_reg [4:0] $end
$scope module a_reg0 $end
$var wire 1 % clk $end
$var wire 1 H d $end
$var wire 1 I rst $end
$var reg 1 J q $end
$upscope $end
$scope module a_reg1 $end
$var wire 1 % clk $end
$var wire 1 K d $end
$var wire 1 L rst $end
$var reg 1 M q $end
$upscope $end
$scope module a_reg2 $end
$var wire 1 % clk $end
$var wire 1 N d $end
$var wire 1 O rst $end
$var reg 1 P q $end
$upscope $end
$scope module a_reg3 $end
$var wire 1 % clk $end
$var wire 1 Q d $end
$var wire 1 R rst $end
$var reg 1 S q $end
$upscope $end
$scope module a_reg4 $end
$var wire 1 % clk $end
$var wire 1 T d $end
$var wire 1 U rst $end
$var reg 1 V q $end
$upscope $end
$scope module b_reg0 $end
$var wire 1 % clk $end
$var wire 1 W d $end
$var wire 1 X rst $end
$var reg 1 Y q $end
$upscope $end
$scope module b_reg1 $end
$var wire 1 % clk $end
$var wire 1 Z d $end
$var wire 1 [ rst $end
$var reg 1 \ q $end
$upscope $end
$scope module b_reg2 $end
$var wire 1 % clk $end
$var wire 1 ] d $end
$var wire 1 ^ rst $end
$var reg 1 _ q $end
$upscope $end
$scope module b_reg3 $end
$var wire 1 % clk $end
$var wire 1 ` d $end
$var wire 1 a rst $end
$var reg 1 b q $end
$upscope $end
$scope module b_reg4 $end
$var wire 1 % clk $end
$var wire 1 c d $end
$var wire 1 d rst $end
$var reg 1 e q $end
$upscope $end
$scope module cout_reg $end
$var wire 1 % clk $end
$var wire 1 f d $end
$var wire 1 g rst $end
$var reg 1 " q $end
$upscope $end
$scope module sum_reg0 $end
$var wire 1 % clk $end
$var wire 1 h d $end
$var wire 1 i rst $end
$var reg 1 j q $end
$upscope $end
$scope module sum_reg1 $end
$var wire 1 % clk $end
$var wire 1 k d $end
$var wire 1 l rst $end
$var reg 1 m q $end
$upscope $end
$scope module sum_reg2 $end
$var wire 1 % clk $end
$var wire 1 n d $end
$var wire 1 o rst $end
$var reg 1 p q $end
$upscope $end
$scope module sum_reg3 $end
$var wire 1 % clk $end
$var wire 1 q d $end
$var wire 1 r rst $end
$var reg 1 s q $end
$upscope $end
$scope module sum_reg4 $end
$var wire 1 % clk $end
$var wire 1 t d $end
$var wire 1 u rst $end
$var reg 1 v q $end
$upscope $end
$upscope $end
$upscope $end
$enddefinitions $end
#0
$dumpvars
xv
zu
xt
xs
zr
xq
xp
zo
xn
xm
zl
xk
xj
zi
xh
zg
xf
xe
zd
0c
xb
za
0`
x_
z^
0]
x\
z[
0Z
xY
zX
0W
xV
zU
0T
xS
zR
0Q
xP
zO
0N
xM
zL
0K
xJ
zI
0H
bx G
bx F
bx0 E
bx D
bx C
bx B
bx A
x@
x?
x>
x=
0<
x;
x:
x9
x8
x7
x6
x5
04
x3
x2
x1
x0
x/
0.
x-
x,
x+
0*
x)
0(
b0 '
b0 &
0%
b0 $
b0 #
x"
bx !
$end
#50
0t
0q
0f
0n
0@
0k
07
0?
00
06
0>
0h
0+
0/
05
0=
0;
b0 A
b0 E
0)
0,
0-
01
02
03
08
09
0:
b0 C
b0 D
0J
0M
0P
0S
b0 G
0V
0Y
0\
0_
0b
b0 F
0e
1%
#100
1W
1H
0%
b1 $
b1 '
b1 #
b1 &
#150
1k
b10 A
b10 E
b1 D
0"
0v
0s
0p
0m
b0 !
b0 B
0j
b1 F
1Y
b1 G
1J
1%
#200
1K
1N
1Q
1T
0%
b11111 #
b11111 &
#250
1f
b111110 E
1@
1+
0k
10
0n
17
0q
1;
0t
1)
1-
13
b0 A
b11110 C
1M
1P
1S
b11111 G
1V
b10 !
b10 B
1m
1%
#300
0W
1Z
1`
0K
0Q
0%
b1010 $
b1010 '
b10101 #
b10101 &
#350
1n
1q
1t
0f
1k
0@
1h
0+
00
07
0;
b11111 A
b0 E
0)
0-
03
b11111 C
b0 D
1"
b0 !
b0 B
0m
1b
1\
b1010 F
0Y
0S
b10101 G
0M
1%
#400
1W
1]
1c
0H
0N
0T
0%
b11111 $
b11111 '
b0 #
b0 &
#450
0J
0P
b0 G
0V
1Y
1_
b11111 F
1e
1j
1m
1p
1s
b11111 !
b11111 B
1v
0"
1%
#500
1H
1K
1N
1Q
1T
0%
b11111 #
b11111 &
#550
1f
1@
1?
17
1t
1>
1q
16
1n
10
1k
0h
1=
15
1/
1+
b11110 A
b111110 E
b0 C
b11111 D
1V
1S
1P
1M
b11111 G
1J
1%
#600
0Z
0%
b11101 $
b11101 '
#650
1n
0k
b111110 E
1)
b11100 A
1+
b10 C
b11101 D
b11101 F
0\
b11110 !
b11110 B
0j
1"
1%
#700
0%
#750
b11100 !
b11100 B
0m
1%
